README
setup.py
bvcs/__init__.py
bvcs/cli.py
bvcs/core.py
bvcs/utils.py
bvcs.egg-info/PKG-INFO
bvcs.egg-info/SOURCES.txt
bvcs.egg-info/dependency_links.txt
bvcs.egg-info/entry_points.txt
bvcs.egg-info/top_level.txt
bvcs/methods/__init__.py
bvcs/methods/attip.py
bvcs/methods/checkout.py
bvcs/methods/clone.py
bvcs/methods/commit.py
bvcs/methods/dumpstate.py
bvcs/methods/identify.py
bvcs/methods/init.py
bvcs/methods/isclean.py
bvcs/methods/outgoing.py
bvcs/methods/pull.py