Metadata-Version: 1.0
Name: bvcs
Version: 0.0.1.dev0
Summary: Asynchronous VCS command runner
Home-page: UNKNOWN
Author: Takafumi Arakaki
Author-email: aka.tkf@gmail.com
License: MIT License
Keywords: vcs,version control system,Git,Mercurial,Bazaar
Platform: UNKNOWN
